CHANGES.rst
MANIFEST.in
README.rst
setup.py
proxy_middleware/__init__.py
proxy_middleware/middleware.py
proxy_middleware.egg-info/PKG-INFO
proxy_middleware.egg-info/SOURCES.txt
proxy_middleware.egg-info/dependency_links.txt
proxy_middleware.egg-info/requires.txt
proxy_middleware.egg-info/top_level.txt